skill_manager/__init__.py
skill_manager/core.py
skill_manager/models.py
skill_manager/server.py
skill_manager/treeshell_functions.py
skill_manager_mcp-0.1.6.dist-info/licenses/LICENSE
skill_manager_mcp-0.1.6.dist-info/METADATA
skill_manager_mcp-0.1.6.dist-info/WHEEL
skill_manager_mcp-0.1.6.dist-info/entry_points.txt
skill_manager_mcp-0.1.6.dist-info/top_level.txt
skill_manager_mcp-0.1.6.dist-info/RECORD
