Metadata-Version: 2.4
Name: skill-manager-mcp
Version: 0.1.6
Summary: Self-steering skill management MCP with RAG-based prediction matching
Author-email: Isaac Wostrel-Rubin <isaac@sanctuary.systems>
License-Expression: LicenseRef-GPBL-1.0
Project-URL: Homepage, https://github.com/sancovp/skill-manager-mcp
Project-URL: Repository, https://github.com/sancovp/skill-manager-mcp
Project-URL: Issues, https://github.com/sancovp/skill-manager-mcp/issues
Keywords: mcp,skills,rag,self-steering,claude-code,compound-intelligence
Classifier: Development Status :: 4 - Beta
Classifier: Intended Audience :: Developers
Classifier: Programming Language :: Python :: 3
Classifier: Programming Language :: Python :: 3.10
Classifier: Programming Language :: Python :: 3.11
Classifier: Programming Language :: Python :: 3.12
Requires-Python: >=3.10
License-File: LICENSE
Requires-Dist: mcp>=1.0.0
Requires-Dist: chromadb>=0.4.0
Requires-Dist: pydantic>=2.0.0
Dynamic: license-file
